{
  "moderation": [
    { "name": "Damla Köksal", "type": "owner" },
    { "name": "Doğancan Koç", "type": "owner" },
    { "name": "Ömer Ayyıldız", "type": "owner" },
    { "name": "Abdullah Şahin", "type": "mod" },
    { "name": "Akif Feyzioğlu", "type": "mod" },
    { "name": "Ahmet İbrahim Aksoy", "type": "mod" },
    { "name": "Malik Masis", "type": "mod" },
    { "name": "Önder Bakırtaş", "type": "mod" }
  ],
  "spacialmembers": [
    { "name": "Engin Demiroğ ", "type": "programmer" },
    { "name": "Selman Kahya", "type": "programmer" },
    { "name": "Merve Ayyüce Kızrak", "type": "programmer" },
    { "name": "Mustafa Murat Çoşkun", "type": "programmer" },
    { "name": "Gökhan Kandemir", "type": "programmer" },
    { "name": "Ömer Savaş", "type": "programmer" },
    { "name": "Muhammed Hilmi Koca", "type": "programmer" },
    { "name": "Eser Ozvataf", "type": "programmer" },
    { "name": "Tarık Güney", "type": "programmer" },
    {
      "name": "Ömer Faruk Uçar | Lezzetli Robot Tarifleri",
      "type": "programmer"
    },
    { "name": "Bora Kaşmer", "type": "programmer" },
    { "name": "Dr. Uzay Çetin", "type": "programmer" },
    { "name": "Ayhan Emre Korucu", "type": "programmer" },
    { "name": "İlge İpek", "type": "programmer" },
    { "name": "Volkan Özçelik", "type": "programmer" },
    { "name": "Abdullah Uğraşkan", "type": "programmer" },
    { "name": "Jaex", "type": "programmer" },
    { "name": "Selçuk Ermaya", "type": "programmer" },
    { "name": "Azmi Mengü", "type": "programmer" },
    { "name": "Alihan Büker", "type": "designer" },
    { "name": "Ferdi Çıldız ", "type": "designer" },
    { "name": "Mahmut Emre Altun", "type": "designer" }
  ],
  "dclink": "https://discord.gg/CjRWT3C9"
}
